{
  "title": "tracks",
  "type": "object",
  "description": "Array of tracks sent as web socket at 5 hz. The SAS will be the server.",
  "examples": [
    {
      "tracks": [
        {
          "id": "ertyu",
          "detectionData": {
            "x1": 5,
            "y1": 7,
            "x2": 10,
            "y2": 15,
            "className": "person"
          },
          "velocity": {
            "vx": 4.5,
            "vy": 3.3
          },
          "trackLocation": {
            "lat": 32.5,
            "lon": 34.7,
            "alt": 78
          },
          "timestamp": 456789044433
        },
        {
          "id": "rtfghj",
          "detectionData": {
            "x1": 20,
            "y1": 35,
            "x2": 25,
            "y2": 46,
            "className": "person"
          },
          "velocity": {
            "vx": 2.9,
            "vy": 3.3
          },
          "trackLocation": {
            "lat": 32.5,
            "lon": 34.6,
            "alt": 45
          },
          "timestamp": 456789044433
        }
      ]
    }
  ],
  "properties": {
    "tracks": {
      "type": "array",
      "items": {
        "$ref": "./track.json"
      }
    },
    "pictureResolution": {
      "type": "string",
      "description": "video resolution (x, y)"
    },
    "sasStatus": {
      "type": "string",
      "enum": [
        "active",
        "inactive"
      ],
      "description": "the external service status"
    }
  },
  "required": [
    "pictureResolution",
    "sasStatus"
  ]
}